[{"type":"block","name":"initial_dialog","content":[{"type":"line","value":" what do you want to talk about?","speaker":"npc"},{"type":"topics","content":[{"type":"topic","name":"Life","mode":"once","content":[{"type":"line","value":"-> about_life"}]},{"type":"topic","name":"The universe","mode":"once","content":[{"type":"line","value":"-> about_universe"}]},{"type":"topic","name":"Everything else...","mode":"once","content":[{"type":"line","value":"-> about_everything_else"}]},{"type":"topic","name":"Goodbye!","mode":"once","content":[{"type":"line","value":"-> goodbye"}]}]}]},{"type":"block","name":"about_life","content":[{"type":"line","value":" I want to talk about life!","speaker":"player"},{"type":"line","value":" Well! That's too complicated...","speaker":"npc"},{"type":"line","value":"<-"}]},{"type":"block","name":"about_universe","content":[{"type":"line","value":" I want to talk about the universe!","speaker":"player"},{"type":"line","value":" That's too complex!","speaker":"npc"},{"type":"line","value":"<-"}]},{"type":"block","name":"about_everything_else","content":[{"type":"line","value":" What about everything else?","speaker":"player"},{"type":"line","value":" I don't have time for this...","speaker":"npc"},{"type":"line","value":"<-"}]},{"type":"block","name":"Goodbye","content":[{"type":"line","value":" See you next time!","speaker":"player"}]}]